odoo9_addon_l10n_ch_scan_bvr-9.0.1.0.0-py2.7-nspkg.pth
odoo_addons/l10n_ch_scan_bvr/__openerp__.py
odoo_addons/l10n_ch_scan_bvr/__init__.py
odoo_addons/l10n_ch_scan_bvr/README.rst
odoo_addons/l10n_ch_scan_bvr/models/partner.py
odoo_addons/l10n_ch_scan_bvr/models/__init__.py
odoo_addons/l10n_ch_scan_bvr/i18n/zh_CN.po
odoo_addons/l10n_ch_scan_bvr/i18n/ru.po
odoo_addons/l10n_ch_scan_bvr/i18n/pt.po
odoo_addons/l10n_ch_scan_bvr/i18n/fr_CH.po
odoo_addons/l10n_ch_scan_bvr/i18n/it.po
odoo_addons/l10n_ch_scan_bvr/i18n/es.po
odoo_addons/l10n_ch_scan_bvr/i18n/nl_BE.po
odoo_addons/l10n_ch_scan_bvr/i18n/ar.po
odoo_addons/l10n_ch_scan_bvr/i18n/lt.po
odoo_addons/l10n_ch_scan_bvr/i18n/ro.po
odoo_addons/l10n_ch_scan_bvr/i18n/tr.po
odoo_addons/l10n_ch_scan_bvr/i18n/hr.po
odoo_addons/l10n_ch_scan_bvr/i18n/bg.po
odoo_addons/l10n_ch_scan_bvr/i18n/es_EC.po
odoo_addons/l10n_ch_scan_bvr/i18n/gl.po
odoo_addons/l10n_ch_scan_bvr/i18n/ca.po
odoo_addons/l10n_ch_scan_bvr/i18n/es_CR.po
odoo_addons/l10n_ch_scan_bvr/i18n/sl.po
odoo_addons/l10n_ch_scan_bvr/i18n/th.po
odoo_addons/l10n_ch_scan_bvr/i18n/cs.po
odoo_addons/l10n_ch_scan_bvr/i18n/pt_PT.po
odoo_addons/l10n_ch_scan_bvr/i18n/et.po
odoo_addons/l10n_ch_scan_bvr/i18n/nl.po
odoo_addons/l10n_ch_scan_bvr/i18n/am.po
odoo_addons/l10n_ch_scan_bvr/i18n/de.po
odoo_addons/l10n_ch_scan_bvr/i18n/vi.po
odoo_addons/l10n_ch_scan_bvr/i18n/fr.po
odoo_addons/l10n_ch_scan_bvr/i18n/pl.po
odoo_addons/l10n_ch_scan_bvr/i18n/pt_BR.po
odoo_addons/l10n_ch_scan_bvr/i18n/el_GR.po
odoo_addons/l10n_ch_scan_bvr/i18n/es_VE.po
odoo_addons/l10n_ch_scan_bvr/i18n/es_MX.po
odoo_addons/l10n_ch_scan_bvr/i18n/fi.po
odoo_addons/l10n_ch_scan_bvr/i18n/hr_HR.po
odoo_addons/l10n_ch_scan_bvr/wizard/scan_bvr_view.xml
odoo_addons/l10n_ch_scan_bvr/wizard/scan_bvr.py
odoo_addons/l10n_ch_scan_bvr/wizard/__init__.py
odoo_addons/l10n_ch_scan_bvr/views/bank_view.xml
odoo_addons/l10n_ch_scan_bvr/views/partner_view.xml
odoo9_addon_l10n_ch_scan_bvr-9.0.1.0.0.dist-info/top_level.txt
odoo9_addon_l10n_ch_scan_bvr-9.0.1.0.0.dist-info/WHEEL
odoo9_addon_l10n_ch_scan_bvr-9.0.1.0.0.dist-info/RECORD
odoo9_addon_l10n_ch_scan_bvr-9.0.1.0.0.dist-info/metadata.json
odoo9_addon_l10n_ch_scan_bvr-9.0.1.0.0.dist-info/DESCRIPTION.rst
odoo9_addon_l10n_ch_scan_bvr-9.0.1.0.0.dist-info/METADATA
odoo9_addon_l10n_ch_scan_bvr-9.0.1.0.0.dist-info/namespace_packages.txt
